costeopy_package/__init__.py
costeopy_package/costeopy.py
costeopy_package-0.2.1.dist-info/LICENSE
costeopy_package-0.2.1.dist-info/METADATA
costeopy_package-0.2.1.dist-info/WHEEL
costeopy_package-0.2.1.dist-info/top_level.txt
costeopy_package-0.2.1.dist-info/RECORD
